{
 
	"article3": {
        "title": "第一篇 三十岁的窈窕淑女(上)",
        "source": ".\\contents\\wanglian\\wanglian3\\网恋 第一篇 三十岁 的窈窕淑女上.txt",
        "pubdate": "2018/01/21",
        "pubby": "厚君",
        "comment": ".\\contents\\wanglian\\wanglian3\\网恋 第一篇 三十岁的窈窕淑女上-Comment.txt",
        "summary": "当今世界的互联网已经成为人类文明的一部分，从需要逐渐成为必须。新闻、通讯、购物等等，用途广泛，不一而足。其中通过网婚，交友婚恋更是这边风景独好。从而发展出《网恋》这个受人玩味的节目，我们时代的文化。"
    },
	"article4": {
        "title": "第一篇 三十岁的窈窕淑女(中)",
        "source": ".\\contents\\wanglian\\wanglian4\\三十岁 的窈窕淑女中.txt",
        "pubdate": "2018/01/21",
        "pubby": "厚君",
        "comment": ".\\contents\\wanglian\\wanglian4\\网恋 第一篇 三十岁的窈窕淑女中-Comment.txt",
        "summary": ""
	},
	"article5": {
        "title": "第一篇 三十岁的窈窕淑女(下)",
        "source": ".\\contents\\wanglian\\wanglian5\\三十岁的窈窕淑女下.txt",
        "pubdate": "2018/01/21",
        "pubby": "厚君",
        "comment": ".\\contents\\wanglian\\wanglian5\\网恋 第一篇 三十岁的窈窕淑女下-Comment.txt",
        "summary": ""
	} ,
	
	"article2": {
        "title": "第二篇 又见少云好天气",
        "source": ".\\contents\\wanglian\\wanglian2\\article2.txt",
        "pubdate": "2018/01/21",
        "pubby": "厚君",
        "comment": ".\\contents\\wanglian\\wanglian2\\comment2.txt",
        "summary": "正在建设中......"
    }
}
 